{
  "name": "MockCL_C003",
  "meta": {
    "survey": "MOCK",
    "data_source": "Mock data for pilot testing",
    "units": {
      "R": "kpc",
      "DeltaSigma": "Msun_per_pc2",
      "sigma": "Msun_per_pc2"
    },
    "cosmo_input": {
      "H0": 70.0,
      "Omega_m": 0.3,
      "Omega_Lambda": 0.7
    },
    "true_params": {
      "M200_1e14": 9.0,
      "c": 4.1,
      "comment": "True NFW parameters used for mock generation"
    }
  },
  "lens": {
    "z": 0.4,
    "name": "MockCL_C003"
  },
  "sources": {
    "z_eff": 1.0,
    "description": "Effective source redshift"
  },
  "profile": [
    {
      "R_kpc": 100.0,
      "DeltaSigma_Msun_pc2": 29115564141.116066,
      "DeltaSigma_err_Msun_pc2": 2973355594.7514324
    },
    {
      "R_kpc": 131.30324344878838,
      "DeltaSigma_Msun_pc2": 11044004958.348759,
      "DeltaSigma_err_Msun_pc2": 1461080213.154624
    },
    {
      "R_kpc": 172.40541740171787,
      "DeltaSigma_Msun_pc2": 5844018907.241526,
      "DeltaSigma_err_Msun_pc2": 695018966.3449335
    },
    {
      "R_kpc": 226.37390492987734,
      "DeltaSigma_Msun_pc2": 2561141325.797291,
      "DeltaSigma_err_Msun_pc2": 315027117.56068516
    },
    {
      "R_kpc": 297.2362794946059,
      "DeltaSigma_Msun_pc2": 990756714.9022058,
      "DeltaSigma_err_Msun_pc2": 131865916.59527425
    },
    {
      "R_kpc": 390.2808756829234,
      "DeltaSigma_Msun_pc2": 371334991.50408953,
      "DeltaSigma_err_Msun_pc2": 47139219.237298705
    },
    {
      "R_kpc": 512.451448332012,
      "DeltaSigma_Msun_pc2": 80289266.94296399,
      "DeltaSigma_err_Msun_pc2": 10370858.009837266
    },
    {
      "R_kpc": 672.8653727602236,
      "DeltaSigma_Msun_pc2": -28439266.39259136,
      "DeltaSigma_err_Msun_pc2": -3872852.310703418
    },
    {
      "R_kpc": 883.4940584779547,
      "DeltaSigma_Msun_pc2": -57578032.94191438,
      "DeltaSigma_err_Msun_pc2": -8098004.953785125
    },
    {
      "R_kpc": 1160.0563544588897,
      "DeltaSigma_Msun_pc2": -42626025.01545848,
      "DeltaSigma_err_Msun_pc2": -8248462.224062299
    },
    {
      "R_kpc": 1523.191619238295,
      "DeltaSigma_Msun_pc2": -39357841.43554826,
      "DeltaSigma_err_Msun_pc2": -7014417.603907481
    },
    {
      "R_kpc": 2000.0000000000002,
      "DeltaSigma_Msun_pc2": -22140716.44662997,
      "DeltaSigma_err_Msun_pc2": -5524862.421798197
    }
  ]
}